[{"wp_inactive_widgets":["block-5","block-6","block-2","block-3","block-4"],"default":["block-7","stm_text-5","block-10","block-12","block-11"],"footer":["stm_text-4","block-9","stm-recent-posts-4","socials-5","mc4wp_form_widget-4","text-1","text-2","text-7"],"shop":["block-8","woocommerce_top_rated_products-4","woocommerce_widget_cart-2"]},{"block":{"7":{"content":"<!-- wp:search {\"label\":\"\",\"buttonText\":\"Search\"} \/-->"},"10":{"content":"<!-- wp:widget-group {\"title\":\"Media Gallery\"} -->\n<h2 class=\"widget-title\">Media Gallery<\/h2><div class=\"wp-widget-group__inner-blocks\"><!-- wp:gallery {\"columns\":4,\"linkTo\":\"none\",\"sizeSlug\":\"full\"} -->\n<figure class=\"wp-block-gallery has-nested-images columns-4 is-cropped\"><!-- wp:image {\"id\":5647,\"sizeSlug\":\"full\",\"linkDestination\":\"none\"} -->\n<figure class=\"wp-block-image size-full\"><img src=\"http:\/\/test.loc\/wp-content\/uploads\/2022\/10\/gallery-1.jpg\" alt=\"motors_placeholder\" class=\"wp-image-5647\"\/><\/figure>\n<!-- \/wp:image -->\n\n<!-- wp:image {\"id\":5648,\"sizeSlug\":\"thumbnail\",\"linkDestination\":\"none\"} -->\n<figure class=\"wp-block-image size-thumbnail\"><img src=\"http:\/\/test.loc\/wp-content\/uploads\/2022\/10\/gallery-3-150x150.jpg\" alt=\"motors_placeholder\" class=\"wp-image-5648\"\/><\/figure>\n<!-- \/wp:image -->\n\n<!-- wp:image {\"id\":5649,\"sizeSlug\":\"full\",\"linkDestination\":\"none\"} -->\n<figure class=\"wp-block-image size-full\"><img src=\"http:\/\/test.loc\/wp-content\/uploads\/2022\/10\/gallery-2.jpg\" alt=\"motors_placeholder\" class=\"wp-image-5649\"\/><\/figure>\n<!-- \/wp:image --><\/figure>\n<!-- \/wp:gallery --><\/div>\n<!-- \/wp:widget-group -->"},"12":{"content":"<!-- wp:widget-group {\"title\":\"Tags\"} -->\n<h2 class=\"widget-title\">Tags<\/h2><div class=\"wp-widget-group__inner-blocks\"><!-- wp:tag-cloud \/--><\/div>\n<!-- \/wp:widget-group -->"},"11":{"content":"<!-- wp:widget-group {\"title\":\"Recent Posts\"} -->\n<h2 class=\"widget-title\">Recent Posts<\/h2><div class=\"wp-widget-group__inner-blocks\"><!-- wp:latest-posts \/--><\/div>\n<!-- \/wp:widget-group -->"},"9":{"content":"<!-- wp:group -->\n<div class=\"wp-block-group\"><!-- wp:widget-group {\"title\":\"Media Gallery\"} -->\n<h2 class=\"widget-title\">Media Gallery<\/h2><div class=\"wp-widget-group__inner-blocks\"><!-- wp:group {\"layout\":{\"type\":\"default\"}} -->\n<div class=\"wp-block-group\"><!-- wp:gallery {\"columns\":4,\"linkTo\":\"none\",\"sizeSlug\":\"thumbnail\"} -->\n<figure class=\"wp-block-gallery has-nested-images columns-4 is-cropped\"><!-- wp:image {\"id\":4889,\"sizeSlug\":\"thumbnail\",\"linkDestination\":\"none\"} -->\n<figure class=\"wp-block-image size-thumbnail\"><img src=\"http:\/\/test.loc\/wp-content\/uploads\/2022\/09\/Ford-F-150_Raptor-1-150x150.jpg\" alt=\"motors_placeholder\" class=\"wp-image-4889\"\/><\/figure>\n<!-- \/wp:image -->\n\n<!-- wp:image {\"id\":5648,\"sizeSlug\":\"full\",\"linkDestination\":\"none\"} -->\n<figure class=\"wp-block-image size-full\"><img src=\"http:\/\/test.loc\/wp-content\/uploads\/2022\/10\/gallery-3.jpg\" alt=\"motors_placeholder\" class=\"wp-image-5648\"\/><\/figure>\n<!-- \/wp:image -->\n\n<!-- wp:image {\"id\":5649,\"sizeSlug\":\"full\",\"linkDestination\":\"none\"} -->\n<figure class=\"wp-block-image size-full\"><img src=\"http:\/\/test.loc\/wp-content\/uploads\/2022\/10\/gallery-2.jpg\" alt=\"motors_placeholder\" class=\"wp-image-5649\"\/><\/figure>\n<!-- \/wp:image -->\n\n<!-- wp:image {\"id\":5543,\"sizeSlug\":\"large\",\"linkDestination\":\"none\"} -->\n<figure class=\"wp-block-image size-large\"><img src=\"http:\/\/test.loc\/wp-content\/uploads\/2021\/03\/01-24-1-1-1024x646.jpg\" alt=\"motors_placeholder\" class=\"wp-image-5543\"\/><\/figure>\n<!-- \/wp:image --><\/figure>\n<!-- \/wp:gallery --><\/div>\n<!-- \/wp:group --><\/div>\n<!-- \/wp:widget-group --><\/div>\n<!-- \/wp:group -->"},"8":{"content":"<!-- wp:widget-group {\"title\":\"PRODUCT CATEGORIES\"} -->\n<h2 class=\"widget-title\">PRODUCT CATEGORIES<\/h2><div class=\"wp-widget-group__inner-blocks\"><!-- wp:woocommerce\/product-categories \/--><\/div>\n<!-- \/wp:widget-group -->"},"5":{"content":"<!-- wp:group --><div class=\"wp-block-group\"><!-- wp:heading --><h2>Archives<\/h2><!-- \/wp:heading --><!-- wp:archives \/--><\/div><!-- \/wp:group -->"},"6":{"content":"<!-- wp:group --><div class=\"wp-block-group\"><!-- wp:heading --><h2>Categories<\/h2><!-- \/wp:heading --><!-- wp:categories \/--><\/div><!-- \/wp:group -->"},"2":{"content":"<!-- wp:search \/-->"},"3":{"content":"<!-- wp:group --><div class=\"wp-block-group\"><!-- wp:heading --><h2>Recent Posts<\/h2><!-- \/wp:heading --><!-- wp:latest-posts \/--><\/div><!-- \/wp:group -->"},"4":{"content":"<!-- wp:group --><div class=\"wp-block-group\"><!-- wp:heading --><h2>Recent Comments<\/h2><!-- \/wp:heading --><!-- wp:latest-comments {\"displayAvatar\":false,\"displayDate\":false,\"displayExcerpt\":false} \/--><\/div><!-- \/wp:group -->"},"_multiwidget":1},"stm_text":{"5":{"title":"TEXT WIDGET","text":"\t\t\t\t<p>\t\t<p><span class=\"stm-small-text\">We know there isn\u2019t much more frustrating than being without your vehicle while it gets repaired.<\/span>Are you ready to give your car the service it is asking for? Schedule car maintenance or repair right here. Our top-notch <a href=\"\/our-services\/\">service staff<\/a> can get your car or truck in and out quickly.<\/p>\t\t\t\t\t<\/p>\n\t\t\t","filter":false,"socials":false},"4":{"title":"Motors Wordpress theme","text":"\t\t\t\t<p>Fusce interdum ipsum egestas urna amet fringilla, et placerat ex venenatis. Aliquet luctus pharetra. Proin sed fringilla lectus\u2026<br \/>\nar sit amet tellus in mollis. Proin nec egestas nibh, eget egestas urna. Phasellus sit amet vehicula nunc. In hac habitasse platea dictumst. <\/p>\t\t\t","filter":false,"socials":false},"_multiwidget":1},"stm-recent-posts":{"4":{"title":"Latest Blog posts","number_of_posts":"1"},"_multiwidget":1},"socials":{"5":{"title":"Social Network","facebook":"#","twitter":"#","vk":"","instagram":"#","behance":"","dribbble":"","flickr":"","git":"","linkedin":"","pinterest":"","yahoo":"","delicious":"","dropbox":"","reddit":"#","soundcloud":"","google":"","google-plus":"","skype":"","youtube":"#","youtube-play":"","tumblr":"","whatsapp":""},"_multiwidget":1},"mc4wp_form_widget":{"4":{"title":"Subscribe"},"_multiwidget":1},"text":{"1":{"title":"Sales Hours","text":"<span class=\"date\">Monday - Friday:<\/span> 09:00AM - 09:00PM\n<span class=\"date\">Saturday:<\/span> 09:00AM - 07:00PM\n<span class=\"date\">Sunday:<\/span> Closed","filter":true,"visual":true},"2":{"title":"Service Hours","text":"<span class=\"date\">Monday - Friday:<\/span> 09:00AM - 09:00PM\n<span class=\"date\">Saturday:<\/span> 09:00AM - 07:00PM\n<span class=\"date\">Sunday:<\/span> Closed","filter":true,"visual":true},"7":{"title":"Parts Hours","text":"<span class=\"date\">Monday - Friday:<\/span> 09:00AM - 09:00PM\n<span class=\"date\">Saturday:<\/span> 09:00AM - 07:00PM\n<span class=\"date\">Sunday:<\/span> Closed","filter":true,"visual":true},"_multiwidget":1},"woocommerce_top_rated_products":{"4":{"title":"Top rated Products","number":5},"_multiwidget":1},"woocommerce_widget_cart":{"2":{"title":"Cart","hide_if_empty":0},"_multiwidget":1}}]